aws_blogs_mcp_server/__init__.py
aws_blogs_mcp_server/bulletproof_search.py
aws_blogs_mcp_server/improved_search.py
aws_blogs_mcp_server/search_validator.py
aws_blogs_mcp_server/server.py
aws_blogs_mcp_server/server_backup.py
aws_blogs_mcp_server/server_fixed.py
aws_blogs_mcp_server-1.0.2.dist-info/METADATA
aws_blogs_mcp_server-1.0.2.dist-info/WHEEL
aws_blogs_mcp_server-1.0.2.dist-info/entry_points.txt
aws_blogs_mcp_server-1.0.2.dist-info/licenses/LICENSE
aws_blogs_mcp_server-1.0.2.dist-info/RECORD
