Metadata-Version: 2.4
Name: aws-blogs-mcp-server
Version: 1.0.2
Summary: MCP server for searching and retrieving AWS blog content
Project-URL: Homepage, https://github.com/chundiv/aws-blogs-mcp-server
Project-URL: Repository, https://github.com/chundiv/aws-blogs-mcp-server
Project-URL: Issues, https://github.com/chundiv/aws-blogs-mcp-server/issues
Author-email: Vinod Chundiv <chundiv@amazon.com>
License: MIT
License-File: LICENSE
Classifier: Development Status :: 4 - Beta
Classifier: Intended Audience :: Developers
Classifier: License :: OSI Approved :: MIT License
Classifier: Programming Language :: Python :: 3
Classifier: Programming Language :: Python :: 3.8
Classifier: Programming Language :: Python :: 3.9
Classifier: Programming Language :: Python :: 3.10
Classifier: Programming Language :: Python :: 3.11
Classifier: Programming Language :: Python :: 3.12
Requires-Python: >=3.8
Requires-Dist: beautifulsoup4>=4.12.0
Requires-Dist: httpx>=0.24.0
Requires-Dist: lxml>=4.9.0
Requires-Dist: mcp>=1.0.0
Provides-Extra: dev
Requires-Dist: black>=23.0.0; extra == 'dev'
Requires-Dist: isort>=5.12.0; extra == 'dev'
Requires-Dist: mypy>=1.0.0; extra == 'dev'
Requires-Dist: pytest-asyncio>=0.21.0; extra == 'dev'
Requires-Dist: pytest>=7.0.0; extra == 'dev'
